Metadata-Version: 2.1
Name: delstat-scraper
Version: 0.1.0
Summary: a webscraper for the penny-del statistic pages
Home-page: https://github.com/grindsa/delstat_scraper
Author: grindsa
Author-email: grindelsack@gmail.com
License: GPL
Platform: any
Classifier: Programming Language :: Python
Classifier: Development Status :: 4 - Beta
Classifier: Natural Language :: German
Classifier: Intended Audience :: Developers
Classifier: License :: OSI Approved :: GNU General Public License v3 or later (GPLv3+)
Classifier: Operating System :: OS Independent
Classifier: Topic :: Software Development :: Libraries :: Python Modules
License-File: LICENSE
